setup.py
climin/__init__.py
climin/adadelta.py
climin/adam.py
climin/asgd.py
climin/base.py
climin/bfgs.py
climin/cg.py
climin/compat.py
climin/gd.py
climin/initialize.py
climin/linesearch.py
climin/mathadapt.py
climin/nes.py
climin/project.py
climin/rmsprop.py
climin/rprop.py
climin/schedule.py
climin/smd.py
climin/util.py
climin.egg-info/PKG-INFO
climin.egg-info/SOURCES.txt
climin.egg-info/dependency_links.txt
climin.egg-info/top_level.txt
climin/stops/__init__.py
climin/stops/stops.py
test/__init__.py
test/common.py
test/losses.py
test/test_adadelta.py
test/test_asgd.py
test/test_bfgs.py
test/test_cg.py
test/test_gd.py
test/test_initialize.py
test/test_lbfgs.py
test/test_linesearch.py
test/test_ncg.py
test/test_nes.py
test/test_rmsprop.py
test/test_rprop.py
test/test_sbfgs.py
test/test_smd.py
test/test_stops.py
test/test_util.py