Metadata-Version: 1.0
Name: climin
Version: 0.1a1
Summary: optimization for machine learning
Home-page: UNKNOWN
Author: UNKNOWN
Author-email: UNKNOWN
License: BSD
Keywords: Machine Learning Optimization
Platform: UNKNOWN
